airflow_prometheus_exporter/__init__.py
airflow_prometheus_exporter/config.yaml
airflow_prometheus_exporter/prometheus_exporter.py
airflow_prometheus_exporter/xcom_config.py
airflow_prometheus_exporter-1.0.8.dist-info/LICENSE
airflow_prometheus_exporter-1.0.8.dist-info/METADATA
airflow_prometheus_exporter-1.0.8.dist-info/WHEEL
airflow_prometheus_exporter-1.0.8.dist-info/entry_points.txt
airflow_prometheus_exporter-1.0.8.dist-info/top_level.txt
airflow_prometheus_exporter-1.0.8.dist-info/RECORD
