Metadata-Version: 2.1
Name: airflow-prometheus-exporter
Version: 1.0.8
Summary: Prometheus Exporter for Airflow Metrics
Home-page: https://github.com/robinhood/airflow_prometheus_exporter
Author: Robinhood Markets, Inc.
Author-email: open-source@robinhood.com
License: BSD 3-Clause
Keywords: airflow_prometheus_exporter
Platform: UNKNOWN
Classifier: Intended Audience :: Developers
Classifier: License :: OSI Approved :: BSD License
Classifier: Natural Language :: English
Classifier: Programming Language :: Python :: 3 :: Only
Classifier: Programming Language :: Python :: 3.6
Classifier: Programming Language :: Python :: 3.7
Requires-Dist: apache-airflow (>=1.10.4)
Requires-Dist: prometheus-client (>=0.4.2)
Provides-Extra: dev
Requires-Dist: bumpversion ; extra == 'dev'
Requires-Dist: tox ; extra == 'dev'
Requires-Dist: twine ; extra == 'dev'
